<bill session="100" type="h" number="3903" updated="2014-03-22T09:53:00-04:00">
  <state datetime="1988-02-03">REFERRED</state>
  <status>
    <introduced datetime="1988-02-03"/>
  </status>
  <introduced datetime="1988-02-03"/>
  <titles>
    <title type="short" as="introduced">Family Farm Tax Accounting Relief Act of 1988</title>
    <title type="official" as="introduced">A bill to amend the Internal Revenue Code of 1986 to exempt farmers from the requirement to capitalize preproductive costs, and to require farmers with large farming operations to use an accrual method of accounting.</title>
  </titles>
  <sponsor id="409423"/>
  <cosponsors>
    <cosponsor id="404587" joined="1988-05-10"/>
    <cosponsor id="404869" joined="1988-02-03"/>
    <cosponsor id="405580" joined="1988-03-15"/>
    <cosponsor id="405646" joined="1988-03-08"/>
    <cosponsor id="300058" joined="1988-03-08"/>
    <cosponsor id="406995" joined="1988-03-16"/>
    <cosponsor id="408180" joined="1988-03-08"/>
    <cosponsor id="408618" joined="1988-03-08"/>
    <cosponsor id="400318" joined="1988-02-03"/>
    <cosponsor id="411834" joined="1988-03-08"/>
    <cosponsor id="411901" joined="1988-03-03"/>
  </cosponsors>
  <actions>
    <action datetime="1988-02-03" state="REFERRED">
      <text>Referred to House Committee on Ways and Means.</text>
    </action>
    <action datetime="1988-11-10">
      <text>Provisions of Measure Incorporated Into H.R.4333.</text>
    </action>
  </actions>
  <committees>
    <committee code="HSWM" name="House Ways and Means" activity="Referral, In Committee"/>
  </committees>
  <relatedbills>
    <bill relation="unknown" session="100" type="h" number="4333"/>
  </relatedbills>
  <subjects>
    <term name="Taxation"/>
    <term name="Accounting"/>
    <term name="Agricultural economics"/>
    <term name="Agriculture and Rural Affairs"/>
    <term name="Corporation taxes"/>
    <term name="Corporations and Stocks"/>
    <term name="Costs"/>
    <term name="Depreciation and amortization"/>
    <term name="Family farms"/>
    <term name="Farm corporations"/>
    <term name="Farmers"/>
    <term name="Farms"/>
    <term name="Income tax"/>
    <term name="Inventories"/>
    <term name="Livestock"/>
    <term name="Poultry"/>
    <term name="Tax deductions"/>
  </subjects>
  <amendments/>
  <summary>2/3/1988--Introduced.
Family Farm Tax Accounting Relief Act of 1988 - Amends the Internal Revenue Code to exempt from the required application of uniform inventory cost capitalization rules any animal produced in a farming business, regardless of the animal's preproductive period. Permits an exception from required use of the accrual method of accounting for family farm corporations having gross receipts of $5,000,000 or less for each prior taxable year after 1985.</summary>
</bill>
