<bill session="100" type="hj" number="58" updated="2014-03-22T09:53:41-04:00">
  <state datetime="1987-01-06">REFERRED</state>
  <status>
    <introduced datetime="1987-01-06"/>
  </status>
  <introduced datetime="1987-01-06"/>
  <titles>
    <title type="official" as="introduced">A joint resolution to provide for the issuance of a commemorative postage stamp in honor of the Columbiettes.</title>
  </titles>
  <sponsor id="409353"/>
  <cosponsors>
    <cosponsor id="400761" joined="1987-04-23"/>
    <cosponsor id="402833" joined="1987-05-07"/>
    <cosponsor id="402928" joined="1987-05-07"/>
    <cosponsor id="300049" joined="1987-07-21"/>
    <cosponsor id="406255" joined="1987-07-21"/>
    <cosponsor id="407432" joined="1987-04-30"/>
    <cosponsor id="407772" joined="1987-04-30"/>
    <cosponsor id="407960" joined="1987-07-21"/>
    <cosponsor id="409237" joined="1987-04-30"/>
    <cosponsor id="300155" joined="1987-07-21"/>
    <cosponsor id="410531" joined="1987-07-21"/>
  </cosponsors>
  <actions>
    <action datetime="1987-01-06" state="REFERRED">
      <text>Referred to House Committee on Post Office and Civil Service.</text>
    </action>
  </actions>
  <committees>
    <committee code="HSPO" name="House Post Office and Civil Service" activity="Referral, In Committee"/>
  </committees>
  <relatedbills/>
  <subjects>
    <term name="Postal service"/>
    <term name="Charities"/>
    <term name="Commemorations"/>
    <term name="Philately"/>
    <term name="Postage stamps"/>
    <term name="Postal Services and Facilities"/>
    <term name="Women's organizations"/>
  </subjects>
  <amendments/>
  <summary>1/6/1987--Introduced.
Requires the Postmaster General to issue a postage stamp honoring the Columbiettes (the ladies' auxiliary of the Knights of Columbus).</summary>
</bill>
