<bill session="100" type="sr" number="493" updated="2014-03-22T09:54:40-04:00">
  <state datetime="1988-10-11">REFERRED</state>
  <status>
    <introduced datetime="1988-10-11"/>
  </status>
  <introduced datetime="1988-10-11"/>
  <titles>
    <title type="official" as="introduced">A resolution to amend Senate Resolution 28 to implement closed caption broadcasting for hearing-impaired individuals of floor proceedings of the Senate.</title>
  </titles>
  <sponsor id="403515"/>
  <cosponsors>
    <cosponsor id="401611" joined="1988-10-11"/>
    <cosponsor id="403171" joined="1988-10-21"/>
    <cosponsor id="406183" joined="1988-10-11"/>
    <cosponsor id="300071" joined="1988-10-11"/>
    <cosponsor id="409917" joined="1988-10-11"/>
    <cosponsor id="410242" joined="1988-10-11"/>
    <cosponsor id="411762" joined="1988-10-11"/>
  </cosponsors>
  <actions>
    <action datetime="1988-10-11" state="REFERRED">
      <text>Referred to the Committee on Rules.</text>
    </action>
  </actions>
  <committees>
    <committee code="SSRA" name="Senate Rules and Administration" activity="Referral, In Committee"/>
  </committees>
  <relatedbills/>
  <subjects>
    <term name="Congress"/>
    <term name="Broadcasting of congressional proceedings"/>
    <term name="Communications and Broadcasting"/>
    <term name="Deaf"/>
    <term name="Disabled"/>
    <term name="Hearing disorders"/>
    <term name="Senate"/>
  </subjects>
  <amendments/>
  <summary>10/11/1988--Introduced.
Amends Senate Resolution 28, 99th Congress, to require closed caption broadcasting of Senate floor proceedings for hearing-impaired individuals.</summary>
</bill>
